textannotate/__init__.py
textannotate/cli.py
textannotate/templates/index.html
textannotate-0.1.0.dist-info/LICENSE
textannotate-0.1.0.dist-info/METADATA
textannotate-0.1.0.dist-info/WHEEL
textannotate-0.1.0.dist-info/entry_points.txt
textannotate-0.1.0.dist-info/top_level.txt
textannotate-0.1.0.dist-info/RECORD
