Metadata-Version: 2.1
Name: textannotate
Version: 0.1.0
Summary: A text classification annotation and review tool developed in Python
Home-page: https://github.com/capjamesg/textannotate
Author: capjamesg
Author-email: readers@jamesg.blog
Classifier: Programming Language :: Python :: 3
Classifier: License :: OSI Approved :: MIT License
Classifier: Operating System :: OS Independent
Requires-Python: >=3.7
License-File: LICENSE
Requires-Dist: flask
Requires-Dist: click
